LLM/__init__.py
LLM/gwdgEngine.py
LLM/ollamaEngine.py
LLM/openaiEngine.py
LLM/synchangeEngine.py
LLM/test_gwdgEngine.py
LLM/test_ollamaEngine.py
agents/__init__.py
agents/agant_tool.py
agents/agent.py
agents/agent_plan.py
agents/agent_sumup.py
agents/agent_tasks.py
agents/trinity.py
cli/__init__.py
cli/main.py
content/__init__.py
content/content_manager.py
content/state.py
pydanticAIagent/__init__.py
pydanticAIagent/content.py
pydanticAIagent/llmodel.py
pydanticAIagent/orchestor.py
pydanticAIagent/plan.py
pydanticAIagent/router.py
pydanticAIagent/state.py
pydanticAIagent/sumup.py
pydanticAIagent/tasks.py
pydanticAIagent/tools_evaluate.py
pydanticAIagent/tools_perpare.py
pydanticAIagent/tools_search.py
toolset/__init__.py
toolset/tool_definition.py
toolset/tool_executor.py
toolset/tool_init_loader.py
toolset/tool_invocation_parser.py
toolset/tool_registry.py
toolset/tool_setup.py
toolset/python_files_to_process/647fc5f24d37467cbe142b50b0fd9b3e.py
toolset/python_files_to_process/a77fa972c7ea4286ad777c137aa1d853.py
toolset/python_files_to_process/cfb9fa3b415444aeb016372d0587fa9b.py
toolset/python_files_to_process/example.py
toolset/python_files_to_process/f1901216535049d89372bbc9520c2198.py
toolset/tools/chatboxEngine.ini
toolset/tools/executeFile.ini
toolset/tools/genCode.ini
toolset/tools/hpcCommand.ini
toolset/tools/mathTool.ini
toolset/tools/plotterTool.ini
toolset/tools/runPython.ini
toolset/tools/sshConnection.ini
toolset/tools/stringLengthTool.ini
toolset/tools/terminalCommand.ini
toolset/tools/chatboxEngine/chatboxEngine.py
toolset/tools/executeFile/executeFile.py
toolset/tools/genCode/config.ini
toolset/tools/genCode/genCode.py
toolset/tools/hpcCommand/hpcCommand.py
toolset/tools/mathTool/mathTool.py
toolset/tools/plotterTool/plotterTool.py
toolset/tools/runPython/runPython.py
toolset/tools/sshConnection/sshConnection.py
toolset/tools/stringLengthTool/stringLengthTool.py
toolset/tools/terminalCommand/terminalCommand.py
lynxnli-0.1.2.dist-info/METADATA
lynxnli-0.1.2.dist-info/WHEEL
lynxnli-0.1.2.dist-info/entry_points.txt
lynxnli-0.1.2.dist-info/top_level.txt
lynxnli-0.1.2.dist-info/RECORD
