Metadata-Version: 2.4
Name: lynxnli
Version: 0.1.2
Summary: A tool for analyzing and visualizing natural language inference (NLI) data
Requires-Python: >=3.12
Requires-Dist: matplotlib>=3.10.1
Requires-Dist: openai>=1.79.0
Requires-Dist: requests==2.32.3
Requires-Dist: dotenv==0.9.9
Requires-Dist: paramiko==3.5.1
